bad4u/__init__.py
bad4u/bad.py
bad4u/utils.py
bad4u-0.1.1.dist-info/METADATA
bad4u-0.1.1.dist-info/WHEEL
bad4u-0.1.1.dist-info/top_level.txt
bad4u-0.1.1.dist-info/RECORD
