Metadata-Version: 2.1
Name: bad4u
Version: 0.1.1
Summary: Una biblioteca de skills
Author: Badreflexz
